mario/__init__.py
mario/attrdict.py
mario/chaining.py
mario/funcs.py
mario/pipeline.py
mario/registry.py
mario/util.py
mario/sinks/__init__.py
mario/sinks/base.py
mario/sinks/mongo.py
mario_python-1.7.0.dist-info/METADATA
mario_python-1.7.0.dist-info/WHEEL
mario_python-1.7.0.dist-info/top_level.txt
mario_python-1.7.0.dist-info/RECORD
