Metadata-Version: 2.1
Name: mario-python
Version: 1.7.0
Summary: A configurable data pipeline library.
Home-page: https://github.com/mitchelllisle/mario
Author: Mitchell Lisle
Author-email: m.lisle90@gmail.com
License: UNKNOWN
Keywords: mario
Platform: UNKNOWN
Requires-Dist: pydantic (<1.6.0,>=1.5.1)
Provides-Extra: mongo
Requires-Dist: pymongo (==3.10.1) ; extra == 'mongo'
